json_lsp/__init__.py
json_lsp/main.py
json_lsp/package.json
json_lsp/yarn.lock
json_lsp/node_modules/.yarn-integrity
json_lsp/node_modules/.bin/installServerIntoExtension
json_lsp/node_modules/.bin/json-languageserver
json_lsp/node_modules/agent-base/.travis.yml
json_lsp/node_modules/agent-base/History.md
json_lsp/node_modules/agent-base/README.md
json_lsp/node_modules/agent-base/index.d.ts
json_lsp/node_modules/agent-base/index.js
json_lsp/node_modules/agent-base/package.json
json_lsp/node_modules/agent-base/patch-core.js
json_lsp/node_modules/agent-base/test/ssl-cert-snakeoil.key
json_lsp/node_modules/agent-base/test/ssl-cert-snakeoil.pem
json_lsp/node_modules/agent-base/test/test.js
json_lsp/node_modules/debug/.coveralls.yml
json_lsp/node_modules/debug/.eslintrc
json_lsp/node_modules/debug/.npmignore
json_lsp/node_modules/debug/.travis.yml
json_lsp/node_modules/debug/CHANGELOG.md
json_lsp/node_modules/debug/LICENSE
json_lsp/node_modules/debug/Makefile
json_lsp/node_modules/debug/README.md
json_lsp/node_modules/debug/karma.conf.js
json_lsp/node_modules/debug/node.js
json_lsp/node_modules/debug/package.json
json_lsp/node_modules/debug/src/browser.js
json_lsp/node_modules/debug/src/debug.js
json_lsp/node_modules/debug/src/index.js
json_lsp/node_modules/debug/src/node.js
json_lsp/node_modules/es6-promise/CHANGELOG.md
json_lsp/node_modules/es6-promise/LICENSE
json_lsp/node_modules/es6-promise/README.md
json_lsp/node_modules/es6-promise/auto.js
json_lsp/node_modules/es6-promise/es6-promise.d.ts
json_lsp/node_modules/es6-promise/package.json
json_lsp/node_modules/es6-promise/dist/es6-promise.auto.js
json_lsp/node_modules/es6-promise/dist/es6-promise.auto.map
json_lsp/node_modules/es6-promise/dist/es6-promise.auto.min.js
json_lsp/node_modules/es6-promise/dist/es6-promise.auto.min.map
json_lsp/node_modules/es6-promise/dist/es6-promise.js
json_lsp/node_modules/es6-promise/dist/es6-promise.map
json_lsp/node_modules/es6-promise/dist/es6-promise.min.js
json_lsp-0.2.0.dist-info/LICENSE
json_lsp-0.2.0.dist-info/METADATA
json_lsp-0.2.0.dist-info/WHEEL
json_lsp-0.2.0.dist-info/entry_points.txt
json_lsp-0.2.0.dist-info/top_level.txt
json_lsp-0.2.0.dist-info/RECORD
