Metadata-Version: 2.1
Name: json-lsp
Version: 0.2.0
Summary: JSON language server Python wrapper
Home-page: https://github.com/martinRenou/json-lsp
Author: Martin Renou
License: BSD 3-Clause
Keywords: Jupyter,JupyterLab,JSON,language-server
Platform: UNKNOWN
Classifier: Intended Audience :: Developers
Classifier: Operating System :: OS Independent
Classifier: Programming Language :: Python :: 3
Classifier: Programming Language :: Python :: 3.6
Classifier: Programming Language :: Python :: 3.7
Classifier: Programming Language :: Python :: 3.8
Classifier: Programming Language :: Python :: 3.9
Classifier: Topic :: Software Development :: Libraries :: Python Modules
Requires-Python: >=3.6
